{"nodes": [{"id": "src_lib_pm_foundations_ts", "label": "pm-foundations.ts", "file_type": "code", "source_file": "src/lib/pm-foundations.ts", "source_location": "L1"}, {"id": "pm_foundations_clampscore1to5", "label": "clampScore1to5()", "file_type": "code", "source_file": "src/lib/pm-foundations.ts", "source_location": "L52"}, {"id": "pm_foundations_mapfivepointtohundred", "label": "mapFivePointToHundred()", "file_type": "code", "source_file": "src/lib/pm-foundations.ts", "source_location": "L61"}, {"id": "pm_foundations_normalizefocus", "label": "normalizeFocus()", "file_type": "code", "source_file": "src/lib/pm-foundations.ts", "source_location": "L66"}, {"id": "pm_foundations_picktopskills", "label": "pickTopSkills()", "file_type": "code", "source_file": "src/lib/pm-foundations.ts", "source_location": "L89"}, {"id": "pm_foundations_clamp", "label": "clamp()", "file_type": "code", "source_file": "src/lib/pm-foundations.ts", "source_location": "L102"}, {"id": "pm_foundations_estimatedaysuntiltarget", "label": "estimateDaysUntilTarget()", "file_type": "code", "source_file": "src/lib/pm-foundations.ts", "source_location": "L107"}, {"id": "pm_foundations_ensurecanonicalskills", "label": "ensureCanonicalSkills()", "file_type": "code", "source_file": "src/lib/pm-foundations.ts", "source_location": "L120"}, {"id": "pm_foundations_ensureskillrows", "label": "ensureSkillRows()", "file_type": "code", "source_file": "src/lib/pm-foundations.ts", "source_location": "L130"}, {"id": "pm_foundations_mapplanfocustolegacy", "label": "mapPlanFocusToLegacy()", "file_type": "code", "source_file": "src/lib/pm-foundations.ts", "source_location": "L157"}], "edges": [{"source": "src_lib_pm_foundations_ts", "target": "pm_foundations_clampscore1to5", "relation": "contains", "confidence": "EXTRACTED", "source_file": "src/lib/pm-foundations.ts", "source_location": "L52", "weight": 1.0}, {"source": "src_lib_pm_foundations_ts", "target": "pm_foundations_mapfivepointtohundred", "relation": "contains", "confidence": "EXTRACTED", "source_file": "src/lib/pm-foundations.ts", "source_location": "L61", "weight": 1.0}, {"source": "src_lib_pm_foundations_ts", "target": "pm_foundations_normalizefocus", "relation": "contains", "confidence": "EXTRACTED", "source_file": "src/lib/pm-foundations.ts", "source_location": "L66", "weight": 1.0}, {"source": "src_lib_pm_foundations_ts", "target": "pm_foundations_picktopskills", "relation": "contains", "confidence": "EXTRACTED", "source_file": "src/lib/pm-foundations.ts", "source_location": "L89", "weight": 1.0}, {"source": "src_lib_pm_foundations_ts", "target": "pm_foundations_clamp", "relation": "contains", "confidence": "EXTRACTED", "source_file": "src/lib/pm-foundations.ts", "source_location": "L102", "weight": 1.0}, {"source": "src_lib_pm_foundations_ts", "target": "pm_foundations_estimatedaysuntiltarget", "relation": "contains", "confidence": "EXTRACTED", "source_file": "src/lib/pm-foundations.ts", "source_location": "L107", "weight": 1.0}, {"source": "src_lib_pm_foundations_ts", "target": "pm_foundations_ensurecanonicalskills", "relation": "contains", "confidence": "EXTRACTED", "source_file": "src/lib/pm-foundations.ts", "source_location": "L120", "weight": 1.0}, {"source": "src_lib_pm_foundations_ts", "target": "prisma", "relation": "imports_from", "confidence": "EXTRACTED", "source_file": "src/lib/pm-foundations.ts", "source_location": "L128", "weight": 1.0}, {"source": "src_lib_pm_foundations_ts", "target": "pm_foundations_ensureskillrows", "relation": "contains", "confidence": "EXTRACTED", "source_file": "src/lib/pm-foundations.ts", "source_location": "L130", "weight": 1.0}, {"source": "src_lib_pm_foundations_ts", "target": "pm_foundations_mapplanfocustolegacy", "relation": "contains", "confidence": "EXTRACTED", "source_file": "src/lib/pm-foundations.ts", "source_location": "L157", "weight": 1.0}, {"source": "pm_foundations_mapfivepointtohundred", "target": "pm_foundations_clampscore1to5", "relation": "calls", "confidence": "EXTRACTED", "source_file": "src/lib/pm-foundations.ts", "source_location": "L62", "weight": 1.0}, {"source": "pm_foundations_ensurecanonicalskills", "target": "pm_foundations_clampscore1to5", "relation": "calls", "confidence": "EXTRACTED", "source_file": "src/lib/pm-foundations.ts", "source_location": "L123", "weight": 1.0}]}