{"nodes": [{"id": "src_emails_reengagement_tsx", "label": "reengagement.tsx", "file_type": "code", "source_file": "src/emails/reengagement.tsx", "source_location": "L1"}], "edges": [{"source": "src_emails_reengagement_tsx", "target": "react", "relation": "imports_from", "confidence": "EXTRACTED", "source_file": "src/emails/reengagement.tsx", "source_location": "L1", "weight": 1.0}, {"source": "src_emails_reengagement_tsx", "target": "components", "relation": "imports_from", "confidence": "EXTRACTED", "source_file": "src/emails/reengagement.tsx", "source_location": "L2", "weight": 1.0}, {"source": "src_emails_reengagement_tsx", "target": "src_emails_layout", "relation": "imports_from", "confidence": "EXTRACTED", "source_file": "src/emails/reengagement.tsx", "source_location": "L3", "weight": 1.0}]}